README.md
setup.cfg
setup.py
bodynavigation/__init__.py
bodynavigation/body_navigation.py
bodynavigation/chest_localization.py
bodynavigation/metrics.py
bodynavigation/organ_detection.py
bodynavigation/organ_detection_algo.py
bodynavigation/patlas.py
bodynavigation/results_drawer.py
bodynavigation/tools.py
bodynavigation/trainer3d.py
bodynavigation/transformation.py
bodynavigation.egg-info/PKG-INFO
bodynavigation.egg-info/SOURCES.txt
bodynavigation.egg-info/dependency_links.txt
bodynavigation.egg-info/requires.txt
bodynavigation.egg-info/top_level.txt
bodynavigation/files/__init__.py