Metadata-Version: 1.1
Name: bodynavigation
Version: 0.3.5
Summary: Body navigation in CT images
Home-page: https://github.com/mjirik/bodynavigation
Author: Miroslav Jirik
Author-email: miroslav.jirik@gmail.com
License: MIT
Keywords: CT navigation medical
Platform: UNKNOWN
Classifier: Development Status :: 3 - Alpha
Classifier: Intended Audience :: Developers
Classifier: Topic :: Scientific/Engineering :: Bio-Informatics
Classifier: License :: OSI Approved :: BSD License
Classifier: Programming Language :: Python :: 3.6
Classifier: Programming Language :: Python :: 3.7
